AUTHORS
COPYING
MANIFEST.in
Makefile
README.md
python-augeas.spec
setup.py
augeas/__init__.py
augeas/ffi.py
python_augeas.egg-info/PKG-INFO
python_augeas.egg-info/SOURCES.txt
python_augeas.egg-info/dependency_links.txt
python_augeas.egg-info/not-zip-safe
python_augeas.egg-info/requires.txt
python_augeas.egg-info/top_level.txt
test/__init__.py
test/test_augeas.py
test/testroot/etc/aliases
test/testroot/etc/auto.master
test/testroot/etc/crontab
test/testroot/etc/crypttab
test/testroot/etc/dnsmasq.conf
test/testroot/etc/ethers
test/testroot/etc/exports
test/testroot/etc/filesystems
test/testroot/etc/fstab
test/testroot/etc/group
test/testroot/etc/grub.conf
test/testroot/etc/host.conf
test/testroot/etc/hosts
test/testroot/etc/hosts.allow
test/testroot/etc/hosts.deny
test/testroot/etc/inittab
test/testroot/etc/krb5.conf
test/testroot/etc/ldap.conf
test/testroot/etc/libuser.conf
test/testroot/etc/logrotate.conf
test/testroot/etc/mail.rc
test/testroot/etc/motd
test/testroot/etc/networks
test/testroot/etc/nsswitch.conf
test/testroot/etc/ntp.conf
test/testroot/etc/passwd
test/testroot/etc/resolv.conf
test/testroot/etc/sensors.conf
test/testroot/etc/smartd.conf
test/testroot/etc/sudoers
test/testroot/etc/sysctl.conf
test/testroot/etc/warnquota.conf
test/testroot/etc/wvdial.conf
test/testroot/etc/yp.conf
test/testroot/etc/yum.conf
test/testroot/etc/mail/access
test/testroot/etc/mail/domaintable
test/testroot/etc/mail/local-host-names
test/testroot/etc/mail/mailertable
test/testroot/etc/mail/sendmail.mc
test/testroot/etc/mail/submit.mc
test/testroot/etc/mail/trusted-users
test/testroot/etc/mail/virtusertable
test/testroot/etc/mail/spamassassin/local.cf
test/testroot/etc/ntp/keys
test/testroot/etc/ntp/ntpservers
test/testroot/etc/ntp/step-tickers
test/testroot/etc/ntp/crypto/pw
test/testroot/etc/ppp/chap-secrets
test/testroot/etc/ppp/ioptions
test/testroot/etc/ppp/options
test/testroot/etc/ppp/pap-secrets
test/testroot/etc/ppp/pppoe-server-options
test/testroot/etc/ppp/peers/wvdial
test/testroot/etc/samba/lmhosts
test/testroot/etc/samba/smb.conf
test/testroot/etc/samba/smbusers
test/testroot/etc/sysconfig/atd
test/testroot/etc/sysconfig/auditd
test/testroot/etc/sysconfig/authconfig
