Metadata-Version: 2.1
Name: python-augeas
Version: 1.2.0
Summary: Python bindings for Augeas
Home-page: http://augeas.net/
Author: Harald Hoyer
Author-email: augeas-devel@redhat.com
Classifier: Programming Language :: Python :: 2.7
Classifier: Programming Language :: Python :: 3.4
Classifier: Programming Language :: Python :: 3.5
Classifier: Programming Language :: Python :: 3.6
Classifier: Programming Language :: Python :: 3.7
Classifier: Programming Language :: Python :: 3.8
Classifier: Programming Language :: Python :: 3.9
Classifier: Programming Language :: Python :: Implementation :: CPython
Classifier: Programming Language :: Python :: Implementation :: PyPy
License-File: COPYING
License-File: AUTHORS
